enocean/__init__.py
enocean/consolelogger.py
enocean/decorators.py
enocean/utils.py
enocean/communicators/__init__.py
enocean/communicators/communicator.py
enocean/communicators/serialcommunicator.py
enocean/communicators/tcpcommunicator.py
enocean/communicators/utils.py
enocean/protocol/EEP.xml
enocean/protocol/__init__.py
enocean/protocol/constants.py
enocean/protocol/crc8.py
enocean/protocol/eep.py
enocean/protocol/packet.py
enocean-0.60.1.data/scripts/enocean_example.py
enocean-0.60.1.dist-info/LICENSE
enocean-0.60.1.dist-info/METADATA
enocean-0.60.1.dist-info/WHEEL
enocean-0.60.1.dist-info/top_level.txt
enocean-0.60.1.dist-info/RECORD
