Metadata-Version: 2.1
Name: enocean
Version: 0.60.1
Summary: EnOcean serial protocol implementation
Home-page: https://github.com/kipe/enocean
Author: Kimmo Huoman
Author-email: kipenroskaposti@gmail.com
License: UNKNOWN
Platform: UNKNOWN
Requires-Dist: enum-compat (>=0.0.2)
Requires-Dist: pyserial (>=3.0)
Requires-Dist: beautifulsoup4 (>=4.3.2)
